CHANGES
LICENSE.txt
MANIFEST.in
README.rst
setup.py
bin/rst2slides
rst2slides/__init__.py
rst2slides/rst2slides.py
rst2slides/rst_directive.py
rst2slides.egg-info/PKG-INFO
rst2slides.egg-info/SOURCES.txt
rst2slides.egg-info/dependency_links.txt
rst2slides.egg-info/requires.txt
rst2slides.egg-info/top_level.txt
rst2slides/data/slideshow.html
rst2slides/data/ui/htmlSlides.js
rst2slides/data/ui/jquery-1.4.2.min.js
rst2slides/data/ui/pygments_style.css
rst2slides/data/ui/styles.css
rst2slides/data/ui/user.css
rst2slides/data/ui/fonts/Candal.ttf
rst2slides/data/ui/fonts/Candal.woff
rst2slides/data/ui/fonts/OFL.txt