Metadata-Version: 1.0
Name: rst2slides
Version: 0.3
Summary: Generates an HTML5 slideshow document from standalone reStructuredText sources.
Home-page: https://bitbucket.org/tin_nqn/rst2slides
Author: Martín Gaitán
Author-email: gaitan@gmail.com
License: GNU GENERAL PUBLIC LICENCE v3.0
Platform: UNKNOWN
Classifier: Development Status :: 3 - Alpha
Classifier: Environment :: Console
Classifier: Intended Audience :: End Users/Desktop
Classifier: License :: OSI Approved :: GNU General Public License (GPL)
Classifier: Natural Language :: English
Classifier: Operating System :: OS Independent
Classifier: Programming Language :: Python
Classifier: Topic :: Software Development :: Documentation
Classifier: Topic :: Text Processing :: Markup
